tsollm/__init__.py
tsollm/core.py
tsollm/exceptions.py
tsollm/schemas.py
tsollm-0.1.3.dist-info/METADATA
tsollm-0.1.3.dist-info/WHEEL
tsollm-0.1.3.dist-info/licenses/LICENSE
tsollm-0.1.3.dist-info/RECORD
