Metadata-Version: 2.4
Name: tsollm
Version: 0.1.3
Summary: Template Structured Output LLM - Predefined schemas for OpenAI Structured Outputs
Project-URL: Homepage, https://github.com/mazzasaverio/tsollm
Project-URL: Documentation, https://tsollm.readthedocs.io/
Project-URL: Repository, https://github.com/mazzasaverio/tsollm
Project-URL: Issues, https://github.com/mazzasaverio/tsollm/issues
Author-email: Saverio Mazza <saverio3107@gmail.com>
Maintainer-email: Saverio Mazza <saverio3107@gmail.com>
License: MIT License
License-File: LICENSE
Keywords: ai,llm,openai,schemas,structured-outputs,templates
Classifier: Development Status :: 4 - Beta
Classifier: Intended Audience :: Developers
Classifier: License :: OSI Approved :: MIT License
Classifier: Programming Language :: Python :: 3
Classifier: Programming Language :: Python :: 3.9
Classifier: Programming Language :: Python :: 3.10
Classifier: Programming Language :: Python :: 3.11
Classifier: Programming Language :: Python :: 3.12
Classifier: Topic :: Scientific/Engineering :: Artificial Intelligence
Classifier: Topic :: Software Development :: Libraries :: Python Modules
Requires-Python: >=3.9
Requires-Dist: openai>=1.0.0
Requires-Dist: pydantic>=2.0.0
Requires-Dist: python-dotenv>=1.0.1
Requires-Dist: typing-extensions>=4.0.0
Provides-Extra: dev
Requires-Dist: black>=23.0.0; extra == 'dev'
Requires-Dist: flake8>=6.0.0; extra == 'dev'
Requires-Dist: isort>=5.0.0; extra == 'dev'
Requires-Dist: mypy>=1.0.0; extra == 'dev'
Requires-Dist: pre-commit>=3.0.0; extra == 'dev'
Requires-Dist: pytest-cov>=4.0.0; extra == 'dev'
Requires-Dist: pytest>=7.0.0; extra == 'dev'
Provides-Extra: docs
Requires-Dist: mkdocs-material>=9.0.0; extra == 'docs'
Requires-Dist: mkdocs>=1.4.0; extra == 'docs'
Requires-Dist: mkdocstrings[python]>=0.20.0; extra == 'docs'
